{
  "friedman": {
    "Q1": {
      "interfaces": [
        "C",
        "D",
        "D1",
        "Y",
        "Y1"
      ],
      "statistic": 29.452914798206287,
      "p_value": 6.324289128467791e-06,
      "n": 12
    },
    "Q2": {
      "interfaces": [
        "C",
        "D",
        "D1",
        "Y",
        "Y1"
      ],
      "statistic": 19.196261682243,
      "p_value": 0.0007191409442459809,
      "n": 12
    },
    "Q3": {
      "interfaces": [
        "C",
        "D",
        "D1",
        "Y",
        "Y1"
      ],
      "statistic": 19.63963963963963,
      "p_value": 0.0005882019603516466,
      "n": 12
    },
    "Q4": {
      "interfaces": [
        "C",
        "D",
        "D1",
        "Y",
        "Y1"
      ],
      "statistic": 16.97297297297296,
      "p_value": 0.0019564607542733275,
      "n": 12
    }
  },
  "pairwise_wilcoxon": {
    "Q1": [
      {
        "interface_a": "C",
        "interface_b": "D",
        "statistic": 0.0,
        "p_value": 0.00048828125,
        "p_value_holm": 0.0048828125,
        "reject_null": true,
        "n": 12
      },
      {
        "interface_a": "C",
        "interface_b": "D1",
        "statistic": 9.5,
        "p_value": 0.0390625,
        "p_value_holm": 0.228515625,
        "reject_null": false,
        "n": 12
      },
      {
        "interface_a": "C",
        "interface_b": "Y",
        "statistic": 28.5,
        "p_value": 0.6962890625,
        "p_value_holm": 0.6962890625,
        "reject_null": false,
        "n": 12
      },
      {
        "interface_a": "C",
        "interface_b": "Y1",
        "statistic": 15.0,
        "p_value": 0.2265625,
        "p_value_holm": 0.6796875,
        "reject_null": false,
        "n": 12
      },
      {
        "interface_a": "D",
        "interface_b": "D1",
        "statistic": 0.0,
        "p_value": 0.001953125,
        "p_value_holm": 0.013671875,
        "reject_null": true,
        "n": 12
      },
      {
        "interface_a": "D",
        "interface_b": "Y",
        "statistic": 0.0,
        "p_value": 0.00048828125,
        "p_value_holm": 0.0048828125,
        "reject_null": true,
        "n": 12
      },
      {
        "interface_a": "D",
        "interface_b": "Y1",
        "statistic": 0.0,
        "p_value": 0.0009765625,
        "p_value_holm": 0.0078125,
        "reject_null": true,
        "n": 12
      },
      {
        "interface_a": "D1",
        "interface_b": "Y",
        "statistic": 12.5,
        "p_value": 0.0380859375,
        "p_value_holm": 0.228515625,
        "reject_null": false,
        "n": 12
      },
      {
        "interface_a": "D1",
        "interface_b": "Y1",
        "statistic": 10.5,
        "p_value": 0.34375,
        "p_value_holm": 0.6875,
        "reject_null": false,
        "n": 12
      },
      {
        "interface_a": "Y",
        "interface_b": "Y1",
        "statistic": 3.0,
        "p_value": 0.046875,
        "p_value_holm": 0.228515625,
        "reject_null": false,
        "n": 12
      }
    ],
    "Q2": [
      {
        "interface_a": "C",
        "interface_b": "D",
        "statistic": 0.0,
        "p_value": 0.001953125,
        "p_value_holm": 0.01953125,
        "reject_null": true,
        "n": 12
      },
      {
        "interface_a": "C",
        "interface_b": "D1",
        "statistic": 6.0,
        "p_value": 0.171875,
        "p_value_holm": 0.515625,
        "reject_null": false,
        "n": 12
      },
      {
        "interface_a": "C",
        "interface_b": "Y",
        "statistic": 10.5,
        "p_value": 0.0498046875,
        "p_value_holm": 0.298828125,
        "reject_null": false,
        "n": 12
      },
      {
        "interface_a": "C",
        "interface_b": "Y1",
        "statistic": 2.0,
        "p_value": 0.00390625,
        "p_value_holm": 0.03125,
        "reject_null": true,
        "n": 12
      },
      {
        "interface_a": "D",
        "interface_b": "D1",
        "statistic": 0.0,
        "p_value": 0.001953125,
        "p_value_holm": 0.01953125,
        "reject_null": true,
        "n": 12
      },
      {
        "interface_a": "D",
        "interface_b": "Y",
        "statistic": 9.0,
        "p_value": 0.125,
        "p_value_holm": 0.5,
        "reject_null": false,
        "n": 12
      },
      {
        "interface_a": "D",
        "interface_b": "Y1",
        "statistic": 24.0,
        "p_value": 0.763671875,
        "p_value_holm": 0.763671875,
        "reject_null": false,
        "n": 12
      },
      {
        "interface_a": "D1",
        "interface_b": "Y",
        "statistic": 20.5,
        "p_value": 0.2822265625,
        "p_value_holm": 0.564453125,
        "reject_null": false,
        "n": 12
      },
      {
        "interface_a": "D1",
        "interface_b": "Y1",
        "statistic": 16.5,
        "p_value": 0.07666015625,
        "p_value_holm": 0.38330078125,
        "reject_null": false,
        "n": 12
      },
      {
        "interface_a": "Y",
        "interface_b": "Y1",
        "statistic": 0.0,
        "p_value": 0.015625,
        "p_value_holm": 0.109375,
        "reject_null": false,
        "n": 12
      }
    ],
    "Q3": [
      {
        "interface_a": "C",
        "interface_b": "D",
        "statistic": 6.5,
        "p_value": 0.0146484375,
        "p_value_holm": 0.087890625,
        "reject_null": false,
        "n": 12
      },
      {
        "interface_a": "C",
        "interface_b": "D1",
        "statistic": 10.0,
        "p_value": 0.08984375,
        "p_value_holm": 0.359375,
        "reject_null": false,
        "n": 12
      },
      {
        "interface_a": "C",
        "interface_b": "Y",
        "statistic": 1.5,
        "p_value": 0.0029296875,
        "p_value_holm": 0.029296875,
        "reject_null": true,
        "n": 12
      },
      {
        "interface_a": "C",
        "interface_b": "Y1",
        "statistic": 1.5,
        "p_value": 0.0029296875,
        "p_value_holm": 0.029296875,
        "reject_null": true,
        "n": 12
      },
      {
        "interface_a": "D",
        "interface_b": "D1",
        "statistic": 5.0,
        "p_value": 0.04296875,
        "p_value_holm": 0.21484375,
        "reject_null": false,
        "n": 12
      },
      {
        "interface_a": "D",
        "interface_b": "Y",
        "statistic": 27.0,
        "p_value": 0.658203125,
        "p_value_holm": 1.0,
        "reject_null": false,
        "n": 12
      },
      {
        "interface_a": "D",
        "interface_b": "Y1",
        "statistic": 19.5,
        "p_value": 0.462890625,
        "p_value_holm": 1.0,
        "reject_null": false,
        "n": 12
      },
      {
        "interface_a": "D1",
        "interface_b": "Y",
        "statistic": 1.5,
        "p_value": 0.005859375,
        "p_value_holm": 0.046875,
        "reject_null": true,
        "n": 12
      },
      {
        "interface_a": "D1",
        "interface_b": "Y1",
        "statistic": 6.0,
        "p_value": 0.00732421875,
        "p_value_holm": 0.05126953125,
        "reject_null": false,
        "n": 12
      },
      {
        "interface_a": "Y",
        "interface_b": "Y1",
        "statistic": 9.0,
        "p_value": 0.515625,
        "p_value_holm": 1.0,
        "reject_null": false,
        "n": 12
      }
    ],
    "Q4": [
      {
        "interface_a": "C",
        "interface_b": "D",
        "statistic": 5.0,
        "p_value": 0.00439453125,
        "p_value_holm": 0.03955078125,
        "reject_null": true,
        "n": 12
      },
      {
        "interface_a": "C",
        "interface_b": "D1",
        "statistic": 0.0,
        "p_value": 0.00390625,
        "p_value_holm": 0.0390625,
        "reject_null": true,
        "n": 12
      },
      {
        "interface_a": "C",
        "interface_b": "Y",
        "statistic": 16.5,
        "p_value": 0.15625,
        "p_value_holm": 0.72265625,
        "reject_null": false,
        "n": 12
      },
      {
        "interface_a": "C",
        "interface_b": "Y1",
        "statistic": 9.0,
        "p_value": 0.064453125,
        "p_value_holm": 0.38671875,
        "reject_null": false,
        "n": 12
      },
      {
        "interface_a": "D",
        "interface_b": "D1",
        "statistic": 13.5,
        "p_value": 0.17578125,
        "p_value_holm": 0.72265625,
        "reject_null": false,
        "n": 12
      },
      {
        "interface_a": "D",
        "interface_b": "Y",
        "statistic": 8.0,
        "p_value": 0.01318359375,
        "p_value_holm": 0.10546875,
        "reject_null": false,
        "n": 12
      },
      {
        "interface_a": "D",
        "interface_b": "Y1",
        "statistic": 1.0,
        "p_value": 0.03125,
        "p_value_holm": 0.21875,
        "reject_null": false,
        "n": 12
      },
      {
        "interface_a": "D1",
        "interface_b": "Y",
        "statistic": 16.0,
        "p_value": 0.14453125,
        "p_value_holm": 0.72265625,
        "reject_null": false,
        "n": 12
      },
      {
        "interface_a": "D1",
        "interface_b": "Y1",
        "statistic": 23.5,
        "p_value": 0.4208984375,
        "p_value_holm": 0.72265625,
        "reject_null": false,
        "n": 12
      },
      {
        "interface_a": "Y",
        "interface_b": "Y1",
        "statistic": 18.0,
        "p_value": 0.185546875,
        "p_value_holm": 0.72265625,
        "reject_null": false,
        "n": 12
      }
    ]
  }
}